lazytools/__init__.py
lazytools/exceptions.py
lazytools/spyder.py
lazytools/to_dataframe.py
lazytools/visualizations.py
lazytools_sflippl-0.0.0.9000.post1.dist-info/DESCRIPTION.rst
lazytools_sflippl-0.0.0.9000.post1.dist-info/METADATA
lazytools_sflippl-0.0.0.9000.post1.dist-info/RECORD
lazytools_sflippl-0.0.0.9000.post1.dist-info/WHEEL
lazytools_sflippl-0.0.0.9000.post1.dist-info/metadata.json
lazytools_sflippl-0.0.0.9000.post1.dist-info/top_level.txt
